start/__init__.py
start/logger.py
start/utils.py
start/cli/__init__.py
start/cli/environment.py
start/cli/inspect.py
start/cli/modify.py
start/cli/params.py
start/cli/project.py
start/core/config.py
start/core/dependency.py
start/core/env_builder.py
start/core/pip_manager.py
start/core/template.py
start_manager-0.7.2.dist-info/LICENSE
start_manager-0.7.2.dist-info/METADATA
start_manager-0.7.2.dist-info/WHEEL
start_manager-0.7.2.dist-info/entry_points.txt
start_manager-0.7.2.dist-info/top_level.txt
start_manager-0.7.2.dist-info/RECORD
